<Profile xmlns:xsi="http://www.w3.org/2001/XMLSchema-instance" xmlns:xsd="http://www.w3.org/2001/XMLSchema"><MemberOfParliamentRole><PersonShortHonorific /><PersonOfficialFirstName>Brian</PersonOfficialFirstName><PersonOfficialLastName>Storseth</PersonOfficialLastName><ConstituencyName>Westlock—St. Paul</ConstituencyName><ConstituencyProvinceTerritoryName>Alberta</ConstituencyProvinceTerritoryName><CaucusShortName>Conservative</CaucusShortName><FromDateTime>2011-05-02T00:00:00</FromDateTime><ToDateTime>2015-10-18T23:59:59</ToDateTime></MemberOfParliamentRole><CaucusMemberRoles /><ParliamentaryPositionRoles /><CommitteeMemberRoles /><ParliamentaryAssociationsandInterparliamentaryGroupRoles /></Profile>