<Profile xmlns:xsi="http://www.w3.org/2001/XMLSchema-instance" xmlns:xsd="http://www.w3.org/2001/XMLSchema"><MemberOfParliamentRole><PersonShortHonorific /><PersonOfficialFirstName>Pierrette</PersonOfficialFirstName><PersonOfficialLastName>Venne</PersonOfficialLastName><ConstituencyName>Saint-Bruno—Saint-Hubert</ConstituencyName><ConstituencyProvinceTerritoryName>Quebec</ConstituencyProvinceTerritoryName><CaucusShortName>Independent Bloc Québécois</CaucusShortName><FromDateTime>2000-11-27T00:00:00</FromDateTime><ToDateTime>2004-06-27T23:59:59</ToDateTime></MemberOfParliamentRole><CaucusMemberRoles /><ParliamentaryPositionRoles /><CommitteeMemberRoles /><ParliamentaryAssociationsandInterparliamentaryGroupRoles /></Profile>